MANIFEST.in
README.rst
bootstrap.py
buildout.cfg
setup.py
antispoofing/__init__.py
antispoofing.eyeblink.egg-info/PKG-INFO
antispoofing.eyeblink.egg-info/SOURCES.txt
antispoofing.eyeblink.egg-info/dependency_links.txt
antispoofing.eyeblink.egg-info/entry_points.txt
antispoofing.eyeblink.egg-info/namespace_packages.txt
antispoofing.eyeblink.egg-info/requires.txt
antispoofing.eyeblink.egg-info/top_level.txt
antispoofing.eyeblink.egg-info/zip-safe
antispoofing/eyeblink/__init__.py
antispoofing/eyeblink/utils.py
antispoofing/eyeblink/script/__init__.py
antispoofing/eyeblink/script/count_blinks.py
antispoofing/eyeblink/script/framediff.py
antispoofing/eyeblink/script/make_movie.py
antispoofing/eyeblink/script/make_scores.py
antispoofing/eyeblink/script/merge_scores.py