Metadata-Version: 1.0
Name: antispoofing.eyeblink
Version: 1.0.4
Summary: Eye-blinking counter-measures for the REPLAY-ATTACK database
Home-page: http://pypi.python.org/pypi/antispoofing.eyeblink
Author: Andre Anjos
Author-email: andre.anjos@idiap.ch
License: GPLv3
Platform: UNKNOWN
